{
 "Allen Pools & Spas, Williston, VT": {
  "match": true,
  "place_id": "ChIJc-9k__Z4ykwR7r9ip7xBO7k",
  "name": "Allen Pools & Spas",
  "formatted_address": "32 Cottonwood Dr #107, Williston, VT 05495, USA",
  "phone": "(802) 288-9028",
  "website": "https://allenpools-spas.com/"
 },
 "Bourbeau Custom Homes, Inc., Swanton, VT": {
  "match": true,
  "place_id": "ChIJHXqwaWgZykwR0XL4p04Vg00",
  "name": "Bourbeau Custom Homes",
  "formatted_address": "4657 Lower Newton Rd, Swanton, VT 05488, USA",
  "phone": "(802) 782-1019",
  "website": "http://www.bhomes.org/"
 },
 "Hayward Design Build, South Hero, VT": {
  "match": true,
  "place_id": "ChIJV0363oVwykwRfPZNCMRw9Xo",
  "name": "Hayward Design Build",
  "formatted_address": "38 Community Ln, South Hero, VT 05486, USA",
  "phone": "(802) 578-3078",
  "website": "http://haywarddesignbuild.com/"
 },
 "Chevalier Drilling Co., Inc., Swanton, VT": {
  "match": true,
  "place_id": "ChIJtduXwUD0yUwRDLPp0jmqd7A",
  "name": "Chevalier Drilling Inc",
  "formatted_address": "3145 US-7, Highgate Springs, VT 05460, USA",
  "phone": "(802) 868-7709",
  "website": "http://www.chevalierdrilling.com/"
 },
 "Colchester Contracting Services, Inc., Colchester, VT": {
  "match": true,
  "place_id": "ChIJ5RJSYdNxykwRR_B47o_6dsc",
  "name": "Colchester Contracting Services, Inc",
  "formatted_address": "97 Blakely Rd Ste 104, Colchester, VT 05446, USA",
  "phone": "(802) 860-9999",
  "website": "http://www.ccsincvt.com/"
 },
 "Dousevicz, Inc., Essex Juntion, VT": {
  "match": true,
  "place_id": "ChIJDbLXtqB3ykwRpoKcYeNx5QU",
  "name": "Dousevicz Inc",
  "formatted_address": "21 Carmichael St, Essex Junction, VT 05452, USA",
  "phone": "(802) 879-4477",
  "website": "http://www.dousevicz.net/"
 },
 "Floor Coverings International, Shelburne, VT": {
  "match": true,
  "place_id": "ChIJWXf9raZ5ykwR6Z1ekGYyiRw",
  "name": "Floor Coverings International",
  "formatted_address": "3910 Shelburne Rd, Shelburne, VT 05482, USA",
  "phone": "(802) 327-8323",
  "website": "https://floorcoveringsinternational.com/locations/us/vt/vermont/"
 },
 "Hayward Design Build, Colchester, VT": {
  "match": true,
  "place_id": "ChIJV0363oVwykwRfPZNCMRw9Xo",
  "name": "Hayward Design Build",
  "formatted_address": "38 Community Ln, South Hero, VT 05486, USA",
  "phone": "(802) 578-3078",
  "website": "http://haywarddesignbuild.com/"
 },
 "Hegeman Electric Inc, Essex Jct., VT": {
  "match": true,
  "place_id": "ChIJHxXaPzV3ykwRUTNgCI9T2ls",
  "name": "Hegeman Electric, Inc.",
  "formatted_address": "16 Gauthier Dr, Essex Junction, VT 05452, USA",
  "phone": "(802) 879-7397",
  "website": "http://www.hegemanelectric.com/"
 },
 "High Performance Modular Homes, Williston, VT": {
  "match": true,
  "place_id": "ChIJ0SqDSc95ykwRfEzSWLoJDy8",
  "name": "High Performance Modular Homes",
  "formatted_address": "528 Essex Rd #205, Williston, VT 05495, USA",
  "phone": "(802) 338-1719",
  "website": "http://www.hpmodular2.com/"
 },
 "BLUE SKY ROOFING, Colchester, VT": {
  "match": true,
  "place_id": "ChIJaQApP6F7ykwRC2HC44bcVYE",
  "name": "Blue Sky Roofing & Custom Exteriors",
  "formatted_address": "41 Duxbury Rd, Richmond, VT 05477, USA",
  "phone": "(802) 862-1500",
  "website": "https://www.blueskyroofingvt.com/"
 },
 "GORDON'S WINDOW DECOR, Williston, VT": {
  "match": true,
  "place_id": "ChIJv0DL1QV5ykwR4iSBh2q4KxY",
  "name": "Gordon's Window Decor",
  "formatted_address": "8 Leroy Rd, Williston, VT 05495, USA",
  "phone": "(802) 655-7777",
  "website": "http://gordonswindowdecor.com/"
 },
 "Applied Solutions Consulting (ASC), Westford, VT": {
  "match": true,
  "place_id": "ChIJ58LEuMYKykwRPFGevPsEa5M",
  "name": "Applied Solutions Consulting (ASC)",
  "formatted_address": "32 Audry Ln, Westford, VT 05494, USA",
  "phone": "(802) 881-3439",
  "website": "https://ascllcvt.com/"
 },
 "Green State Builders, Essex Jct, VT": {
  "match": true,
  "place_id": "ChIJVVXZx39wykwRHL1IYu8xVag",
  "name": "Green State Builders, LLC",
  "formatted_address": "6d Laurette Dr, Essex, VT 05452, USA",
  "phone": "(802) 497-0314",
  "website": "https://www.greenstatebuildersvt.com/"
 },
 "Culligan Water Technologies, Colchester, VT": {
  "match": true,
  "place_id": "ChIJv3ydlmtyykwRmMJ2K5ixD-Y",
  "name": "Culligan Water Conditioning of The Green Mountain",
  "formatted_address": "154 Brentwood Dr #1, Colchester, VT 05446, USA",
  "phone": "(802) 865-0000",
  "website": "https://culligan4u.com/?utm_source=google&utm_medium=gmb&utm_campaign=colchester"
 },
 "Godbout Development, Williston, VT": {
  "match": false,
  "status": "OK",
  "candidate_count": 5,
  "candidates": [
   {
    "name": "Cottage Hill Estates",
    "formatted_address": "Cottage Rd, Hinesburg, VT 05461"
   },
   {
    "name": "Preferred Properties",
    "formatted_address": "149 Knight Ln, Williston, VT 05495"
   },
   {
    "name": "Taft Corners Shopping Center",
    "formatted_address": "Taft Corners Shopping Center, Williston, VT 05495"
   },
   {
    "name": "Rem Development Co LLC",
    "formatted_address": "599 Avenue D, Williston, VT 05495"
   },
   {
    "name": "Milot Real Estate",
    "formatted_address": "32 Seymour St #101, Williston, VT 05495"
   }
  ]
 },
 "H.J. LeBoeuf & Son, Inc., Vergennes, VT": {
  "match": false,
  "status": "ZERO_RESULTS",
  "candidate_count": 0,
  "candidates": []
 },
 "Builders Installed Products, Williston, VT": {
  "match": false,
  "status": "OK",
  "candidate_count": 12,
  "candidates": [
   {
    "name": "Builders Installed Products of Vermont",
    "formatted_address": "51 Industrial Park Dr, Westmoreland, NH 03467"
   },
   {
    "name": "Building Energy",
    "formatted_address": "1570 S Brownell Rd, Williston, VT 05495"
   },
   {
    "name": "Lansing Building Products - Burlington, VT",
    "formatted_address": "71 Leroy Rd, Williston, VT 05495"
   },
   {
    "name": "ABC Supply Co. Inc.",
    "formatted_address": "78 Adams Dr, Williston, VT 05495"
   },
   {
    "name": "QXO",
    "formatted_address": "391 Boyer Cir, Williston, VT 05495"
   },
   {
    "name": "L&W Supply - Williston, VT",
    "formatted_address": "121 Commerce St, Williston, VT 05495"
   },
   {
    "name": "Builders Installed Products",
    "formatted_address": "10 Printers Square Suite 14, Hermon, ME 04401"
   },
   {
    "name": "Builders Installed Products Maine",
    "formatted_address": "515 Riverside Industrial Pkwy, Portland, ME 04103"
   },
   {
    "name": "Builders Installed Products",
    "formatted_address": "136 Tivoli St, Albany, NY 12207"
   },
   {
    "name": "BBCI Attic-Solution & Insulation's & Roofing Service Essex Junction, VT",
    "formatted_address": "48 Cascade St, Essex Junction, VT 05452"
   },
   {
    "name": "Builders Installed Products New Hampshire",
    "formatted_address": "48 King St, Auburn, NH 03032"
   },
   {
    "name": "Burlington Insulation Therma Pros",
    "formatted_address": "160 Main St Ste 100A, Burlington, VT 05401"
   }
  ]
 },
 "168 WOODS HOLLOW DRIVE, Milton, VT": {
  "match": false,
  "status": "BARE_ADDRESS_NO_BUSINESS",
  "candidate_count": 1,
  "candidates": [
   {
    "name": "168 Woods Hollow Dr",
    "formatted_address": "168 Woods Hollow Dr, Milton, VT 05468"
   }
  ]
 },
 "COLLETTE Electric, Milton, VT": {
  "match": false,
  "status": "OK",
  "candidate_count": 8,
  "candidates": [
   {
    "name": "Cole Electric Inc",
    "formatted_address": "205 Church Ln, Thetford, VT 05074"
   },
   {
    "name": "Lakeside Electric Inc.",
    "formatted_address": "2041 Williston Rd, South Burlington, VT 05403"
   },
   {
    "name": "Milton Electrical Services",
    "formatted_address": "478 Lake Rd, Milton, VT 05468"
   },
   {
    "name": "Newton Electric",
    "formatted_address": "30 Cobble Hill Rd, Milton, VT 05468"
   },
   {
    "name": "Catamount Electric",
    "formatted_address": "Old Farm Rd, West Burke, VT 05871"
   },
   {
    "name": "COLLINS ELECTRIC",
    "formatted_address": "3 S Main St #1186, Barre, VT 05641"
   },
   {
    "name": "Koletas Electric",
    "formatted_address": "39 S Main St, Schaghticoke, NY 12154"
   },
   {
    "name": "Tougas Electric",
    "formatted_address": "64 Hidden Meadow, Milton, VT 05468"
   }
  ]
 },
 "289 Rudgate Rd, Colchester, VT": {
  "match": false,
  "status": "BARE_ADDRESS_NO_BUSINESS",
  "candidate_count": 1,
  "candidates": [
   {
    "name": "289 Rudgate Rd",
    "formatted_address": "289 Rudgate Rd, Colchester, VT 05446"
   }
  ]
 },
 "29 LOALDO DR., Burlington, VT": {
  "match": false,
  "status": "BARE_ADDRESS_NO_BUSINESS",
  "candidate_count": 1,
  "candidates": [
   {
    "name": "29 Loaldo Dr",
    "formatted_address": "29 Loaldo Dr, Burlington, VT 05408"
   }
  ]
 },
 "POQUETTE Heating, Burlington, VT": {
  "match": false,
  "status": "OK",
  "candidate_count": 4,
  "candidates": [
   {
    "name": "Paquette Plumbing",
    "formatted_address": "125 Valley View #1, Mendon, VT 05701"
   },
   {
    "name": "Hulbert Supply",
    "formatted_address": "332 Pine St, Burlington, VT 05401"
   },
   {
    "name": "Laplante's Plumbing & Heating LLC",
    "formatted_address": "127 Gilly Dr, Colchester, VT 05446"
   },
   {
    "name": "Stanley Harris & Sons Plumbing & Heating",
    "formatted_address": "83 Claire Point Rd, Burlington, VT 05408"
   }
  ]
 },
 "51 Dufresne Drive, Winooski, VT": {
  "match": false,
  "status": "BARE_ADDRESS_NO_BUSINESS",
  "candidate_count": 1,
  "candidates": [
   {
    "name": "51 Dufresne Dr",
    "formatted_address": "51 Dufresne Dr, Winooski, VT 05404"
   }
  ]
 },
 "CRETE Plumbing, Winooski, VT": {
  "match": true,
  "place_id": "ChIJIy1M_Hl6ykwRW1KMdpu26sg",
  "name": "Yankee Plumbing & Heating Inc",
  "formatted_address": "235 Main St Unit 3, Winooski, VT 05404, USA",
  "phone": "(802) 655-1918",
  "website": null
 },
 "6 June Way, Milton, VT": {
  "match": false,
  "status": "BARE_ADDRESS_NO_BUSINESS",
  "candidate_count": 1,
  "candidates": [
   {
    "name": "6 June Way",
    "formatted_address": "6 June Way, Milton, VT 05468"
   }
  ]
 },
 "73 HARVEY RD, Underhill, VT": {
  "match": false,
  "status": "BARE_ADDRESS_NO_BUSINESS",
  "candidate_count": 1,
  "candidates": [
   {
    "name": "73 Harvey Rd",
    "formatted_address": "73 Harvey Rd, Underhill, VT 05489"
   }
  ]
 },
 "STREK Heating, Underhill, VT": {
  "match": false,
  "status": "OK",
  "candidate_count": 2,
  "candidates": [
   {
    "name": "Williamson Plumbing & Heating, Inc.",
    "formatted_address": "444 Shunpike Rd, Williston, VT 05495"
   },
   {
    "name": "Green Heat",
    "formatted_address": "38 Pinehurst Dr, Jericho, VT 05465"
   }
  ]
 },
 "75 NORTHVIEW DRIVE, Burlington, VT": {
  "match": false,
  "status": "BARE_ADDRESS_NO_BUSINESS",
  "candidate_count": 1,
  "candidates": [
   {
    "name": "75 Northview Dr",
    "formatted_address": "75 Northview Dr, Burlington, VT 05408"
   }
  ]
 },
 "KONJUHOVAC Electric, Burlington, VT": {
  "match": false,
  "status": "OK",
  "candidate_count": 3,
  "candidates": [
   {
    "name": "Lakeside Electric Inc.",
    "formatted_address": "2041 Williston Rd, South Burlington, VT 05403"
   },
   {
    "name": "Kiehl Electic",
    "formatted_address": "209 Lakewood Pkwy, Burlington, VT 05408"
   },
   {
    "name": "Cummings Electric",
    "formatted_address": "80 Ethan Allen Dr, South Burlington, VT 05403"
   }
  ]
 },
 "95 Plains Rd, Jericho, VT": {
  "match": false,
  "status": "BARE_ADDRESS_NO_BUSINESS",
  "candidate_count": 1,
  "candidates": [
   {
    "name": "95 Plains Rd",
    "formatted_address": "95 Plains Rd, Jericho, VT 05465"
   }
  ]
 },
 "Fischer Heating, Jericho, VT": {
  "match": true,
  "place_id": "ChIJXd2pwQOJtUwRq59U7RqVx-k",
  "name": "Fisher's Heating & Gas",
  "formatted_address": "89 Plains Rd, Jericho, VT 05465, USA",
  "phone": "(802) 899-4099",
  "website": "http://fischersheatingvt.com/"
 },
 "126 Sadie Lane, South Burlington, VT": {
  "match": false,
  "status": "BARE_ADDRESS_NO_BUSINESS",
  "candidate_count": 1,
  "candidates": [
   {
    "name": "126 Sadie Ln",
    "formatted_address": "126 Sadie Ln, South Burlington, VT 05403"
   }
  ]
 },
 "14 Hughes Court, Milton, VT": {
  "match": false,
  "status": "BARE_ADDRESS_NO_BUSINESS",
  "candidate_count": 1,
  "candidates": [
   {
    "name": "14 Hughes Ct",
    "formatted_address": "14 Hughes Ct, Milton, VT 05468"
   }
  ]
 },
 "PROVOST Electric, Milton, VT": {
  "match": false,
  "status": "ZERO_RESULTS",
  "candidate_count": 0,
  "candidates": []
 },
 "23 Ducks Court, Milton, VT": {
  "match": false,
  "status": "BARE_ADDRESS_NO_BUSINESS",
  "candidate_count": 1,
  "candidates": [
   {
    "name": "23 Ducks Ct",
    "formatted_address": "23 Ducks Ct, Milton, VT 05468"
   }
  ]
 },
 "571 Middle Road, Milton, VT": {
  "match": false,
  "status": "BARE_ADDRESS_NO_BUSINESS",
  "candidate_count": 1,
  "candidates": [
   {
    "name": "571 Middle Rd",
    "formatted_address": "571 Middle Rd, Milton, VT 05468"
   }
  ]
 },
 "Stuart Electric, Milton, VT": {
  "match": false,
  "status": "OK",
  "candidate_count": 7,
  "candidates": [
   {
    "name": "Stewart Electrical Contracting, Inc.",
    "formatted_address": "670 S Union St, Lawrence, MA 01843"
   },
   {
    "name": "Stuart Electric Supply",
    "formatted_address": "3003 S 300 W, Salt Lake City, UT 84115"
   },
   {
    "name": "Stewart Electrical LLC",
    "formatted_address": "353 Patterson Rd, Dresden, ME 04342"
   },
   {
    "name": "Stuart Electric",
    "formatted_address": "480 Town Ctr St, Mooresville, IN 46158"
   },
   {
    "name": "Newton Electric",
    "formatted_address": "30 Cobble Hill Rd, Milton, VT 05468"
   },
   {
    "name": "Tougas Electric",
    "formatted_address": "64 Hidden Meadow, Milton, VT 05468"
   },
   {
    "name": "Stuart Electric",
    "formatted_address": "370 S Main St, Fillmore, UT 84631"
   }
  ]
 },
 "690 HINESBURG HOLLOW ROAD, Huntington, VT": {
  "match": false,
  "status": "BARE_ADDRESS_NO_BUSINESS",
  "candidate_count": 1,
  "candidates": [
   {
    "name": "690 Hinesburg Hollow Rd",
    "formatted_address": "690 Hinesburg Hollow Rd, Huntington, VT 05462"
   }
  ]
 },
 "75 Anna's Court, Colchester, VT": {
  "match": false,
  "status": "BARE_ADDRESS_NO_BUSINESS",
  "candidate_count": 1,
  "candidates": [
   {
    "name": "75 Annas Ct",
    "formatted_address": "75 Annas Ct, Colchester, VT 05446"
   }
  ]
 },
 "LABELLE Heating, Colchester, VT": {
  "match": false,
  "status": "OK",
  "candidate_count": 7,
  "candidates": [
   {
    "name": "Laplante's Plumbing & Heating LLC",
    "formatted_address": "127 Gilly Dr, Colchester, VT 05446"
   },
   {
    "name": "Red Rock Mechanical, LLC",
    "formatted_address": "339 Red Rock Rd, Colchester, VT 05446"
   },
   {
    "name": "LaBelle Plumbing",
    "formatted_address": "330 Jamaica Point Rd, Rome, ME 04963"
   },
   {
    "name": "A Cooper Mechanical, Inc.",
    "formatted_address": "171 Leroy Rd, Williston, VT 05495"
   },
   {
    "name": "Benoure Plumbing, Heating & Air Conditioning",
    "formatted_address": "34 Commerce Ave, South Burlington, VT 05403"
   },
   {
    "name": "Chuck's Heating & A/C, Inc",
    "formatted_address": "416 Roosevelt Hwy, Colchester, VT 05446"
   },
   {
    "name": "Chase Plumbing & Heating",
    "formatted_address": "55 Bayview Rd, Colchester, VT 05446"
   }
  ]
 },
 "94 HUNTING RIDGE LANE, Milton, VT": {
  "match": false,
  "status": "BARE_ADDRESS_NO_BUSINESS",
  "candidate_count": 1,
  "candidates": [
   {
    "name": "94 Hunting Ridge Ln",
    "formatted_address": "94 Hunting Ridge Ln, Milton, VT 05468"
   }
  ]
 },
 "BRUNELLE Heating, Milton, VT": {
  "match": false,
  "status": "OK",
  "candidate_count": 8,
  "candidates": [
   {
    "name": "Bourne's Energy",
    "formatted_address": "797 US-7, Milton, VT 05468"
   },
   {
    "name": "Bourne's Energy",
    "formatted_address": "72 Lower Main St, Morrisville, VT 05661"
   },
   {
    "name": "Benoure Plumbing, Heating & Air Conditioning",
    "formatted_address": "34 Commerce Ave, South Burlington, VT 05403"
   },
   {
    "name": "Laplante's Plumbing & Heating LLC",
    "formatted_address": "127 Gilly Dr, Colchester, VT 05446"
   },
   {
    "name": "Brock's Plumbing, Heating & Air Conditioning",
    "formatted_address": "268 N Main St Suite#2, St Albans City, VT 05478"
   },
   {
    "name": "Burnell's Plumbing and Heating LLC",
    "formatted_address": "168 Main St, Hudson Falls, NY 12839"
   },
   {
    "name": "Stanley Harris & Sons Plumbing & Heating",
    "formatted_address": "83 Claire Point Rd, Burlington, VT 05408"
   },
   {
    "name": "Cornell Plumbing & Heating Inc",
    "formatted_address": "450 Mt Hunger Rd, Lyndonville, VT 05851"
   }
  ]
 },
 "96 Muirfield Road, Burlington, VT": {
  "match": false,
  "status": "BARE_ADDRESS_NO_BUSINESS",
  "candidate_count": 1,
  "candidates": [
   {
    "name": "96 Muirfield Rd",
    "formatted_address": "96 Muirfield Rd, Burlington, VT 05408"
   }
  ]
 },
 "Pobric Electric, Burlington, VT": {
  "match": false,
  "status": "OK",
  "candidate_count": 4,
  "candidates": [
   {
    "name": "RG Electric LLC, VT",
    "formatted_address": "39 Park St unit 1, Essex Junction, VT 05452"
   },
   {
    "name": "Burlington Electric Department",
    "formatted_address": "585 Pine St #4864, Burlington, VT 05401"
   },
   {
    "name": "Lakeside Electric Inc.",
    "formatted_address": "2041 Williston Rd, South Burlington, VT 05403"
   },
   {
    "name": "Joseph C. McNeil Generating Station",
    "formatted_address": "111 Intervale Rd, Burlington, VT 05401"
   }
  ]
 }
}